MANIFEST.in
README.rst
setup.cfg
setup.py
indexbuilder/SearchBuildTargets.py
indexbuilder/TagFinder.py
indexbuilder/Untitled.py
indexbuilder/__init__.py
sphinxcontrib/SearchBuildTargets.py
sphinxcontrib/TagFinder.py
sphinxcontrib/__init__.py
sphinxcontrib/tests/__init__.py
sphinxcontrib/tests/test_SearchBuildTargets.py
sphinxcontrib/tests/test_tagfinder.py
sphinxcontrib_indexbuilder.egg-info/PKG-INFO
sphinxcontrib_indexbuilder.egg-info/SOURCES.txt
sphinxcontrib_indexbuilder.egg-info/dependency_links.txt
sphinxcontrib_indexbuilder.egg-info/entry_points.txt
sphinxcontrib_indexbuilder.egg-info/namespace_packages.txt
sphinxcontrib_indexbuilder.egg-info/not-zip-safe
sphinxcontrib_indexbuilder.egg-info/requires.txt
sphinxcontrib_indexbuilder.egg-info/top_level.txt
tests/__init__.py
tests/test_SearchBuildTargets.py
tests/test_tagfinder.py