Metadata-Version: 1.1
Name: sphinxcontrib-indexbuilder
Version: 0.1.2
Summary: sphinx index building tools
Home-page: https://github.com/goingmywaynet/sphinxcontrib-indexbuilder
Author: Joey Chen
Author-email: joey-tech@goingmyway.net
License: MIT
Keywords: sphinx,sphinxcontrib,smb,windows,link,share
Platform: any
Classifier: Development Status :: 3 - Alpha
Classifier: Environment :: Console
Classifier: Environment :: Web Environment
Classifier: Intended Audience :: Developers
Classifier: License :: OSI Approved :: MIT License
Classifier: Natural Language :: Japanese
Classifier: Operating System :: Microsoft :: Windows
Classifier: Programming Language :: Python
Classifier: Topic :: Documentation
Classifier: Topic :: Utilities
